index_bam_by_read_id.py
test_index_bam_by_read.py
index_bam_by_read_id-0.1.8.data/scripts/bam_reads_by_id
index_bam_by_read_id-0.1.8.dist-info/DESCRIPTION.rst
index_bam_by_read_id-0.1.8.dist-info/METADATA
index_bam_by_read_id-0.1.8.dist-info/RECORD
index_bam_by_read_id-0.1.8.dist-info/WHEEL
index_bam_by_read_id-0.1.8.dist-info/metadata.json
index_bam_by_read_id-0.1.8.dist-info/top_level.txt
